README.rst
caimaoy_util.py
setup.py
caimaoy_util.egg-info/PKG-INFO
caimaoy_util.egg-info/SOURCES.txt
caimaoy_util.egg-info/dependency_links.txt
caimaoy_util.egg-info/top_level.txt
caimaoy_util.egg-info/zip-safe