Metadata-Version: 1.1
Name: caimaoy-util
Version: 0.0.1.6.alpha
Summary: caimaoy's util
Home-page: https://github.com/caimaoy
Author: caimaoy
Author-email: caimaoy@gmail.com
License: MIT
Keywords: caimaoy python util
Platform: UNKNOWN
Classifier: License :: OSI Approved :: MIT License
Classifier: Programming Language :: Python
Classifier: Intended Audience :: Developers
Classifier: Operating System :: Microsoft
